effect_py/__init__.py
effect_py/contracts.py
effect_py/either.py
fn_effect_py-0.0.1.dist-info/METADATA
fn_effect_py-0.0.1.dist-info/WHEEL
fn_effect_py-0.0.1.dist-info/RECORD
