Metadata-Version: 2.4
Name: fn-effect-py
Version: 0.0.1
Summary: 
Requires-Python: >=3.13
Classifier: Programming Language :: Python :: 3
Classifier: Programming Language :: Python :: 3.13
Classifier: Programming Language :: Python :: 3.14
Requires-Dist: pydantic (>=2.12.4,<3.0.0)
Requires-Dist: tqdm (>=4.67.1,<5.0.0)
